rs_tools/__init__.py
rs_tools/implicit_wrapper.py
rs_tools/utils.py
rs_tools-0.1.dist-info/METADATA
rs_tools-0.1.dist-info/WHEEL
rs_tools-0.1.dist-info/top_level.txt
rs_tools-0.1.dist-info/RECORD
