Metadata-Version: 2.1
Name: rs-tools
Version: 0.1
Summary: Recommender systems related tools
Home-page: https://github.com/darel13712/rs_tools
Author: Darel
Author-email: darel142857@gmail.com
License: UNKNOWN
Platform: UNKNOWN
Classifier: Programming Language :: Python :: 3
Classifier: License :: OSI Approved :: MIT License
Classifier: Operating System :: OS Independent
Requires-Python: >=3.6
Requires-Dist: pandas
Requires-Dist: numpy
Requires-Dist: implicit
Requires-Dist: scipy
Requires-Dist: sklearn
